palme/__init__.py
palme/model.py
palme/transformer.py
palme-0.1.2.dist-info/LICENSE
palme-0.1.2.dist-info/WHEEL
palme-0.1.2.dist-info/METADATA
palme-0.1.2.dist-info/RECORD
